cherry_shared/InfoService.py
cherry_shared/__init__.py
cherry_shared/blockchains.py
cherry_shared/bot_strings.py
cherry_shared/constants.py
cherry_shared/emojis.py
cherry_shared/functions.py
cherry_shared/launchpads.py
cherry_shared/types/__init__.py
cherry_shared/types/blockchain.py
cherry_shared/types/dexscreener.py
cherry_shared/types/launchpad.py
cherry_shared/types/leaderboardEntry.py
cherry_shared/types/raid_info.py
cherry_shared/types/user_wallet.py
cherry_shared2-0.1.31.dist-info/METADATA
cherry_shared2-0.1.31.dist-info/WHEEL
cherry_shared2-0.1.31.dist-info/top_level.txt
cherry_shared2-0.1.31.dist-info/RECORD
