Metadata-Version: 2.4
Name: cherry_shared2
Version: 0.1.31
Summary: Cherry Bot shared utilities
Author: headria
Classifier: Development Status :: 4 - Beta
Classifier: Intended Audience :: Developers
Classifier: Programming Language :: Python :: 3
Classifier: Programming Language :: Python :: 3.11
Classifier: Programming Language :: Python :: 3.12
Requires-Python: >=3.11
Requires-Dist: web3
Requires-Dist: pyrogram
Requires-Dist: aiohttp
Dynamic: author
Dynamic: classifier
Dynamic: description
Dynamic: description-content-type
Dynamic: requires-dist
Dynamic: requires-python
Dynamic: summary
